pynever/__init__.py
pynever/datasets.py
pynever/exceptions.py
pynever/networks.py
pynever/nodes.py
pynever/utilities.py
pynever/config/__init__.py
pynever/config/configuration.ini
pynever/legacy/ReLU Over-approx.ipynb
pynever/legacy/Sigmoid Over-approx.ipynb
pynever/legacy/bidimensional_example_FC_ReLU.ipynb
pynever/legacy/bidimensional_example_FC_ReLU_Complete.ipynb
pynever/legacy/bidimensional_example_FC_ReLU_Overapprox.ipynb
pynever/legacy/bidimensional_example_with_sigmoid.ipynb
pynever/legacy/tensors.py
pynever/legacy/visualization.py
pynever/scripts/__init__.py
pynever/scripts/cli.py
pynever/strategies/__init__.py
pynever/strategies/pruning.py
pynever/strategies/training.py
pynever/strategies/abstraction/__init__.py
pynever/strategies/abstraction/linearfunctions.py
pynever/strategies/abstraction/networks.py
pynever/strategies/abstraction/nodes.py
pynever/strategies/abstraction/star.py
pynever/strategies/abstraction/bounds_propagation/__init__.py
pynever/strategies/abstraction/bounds_propagation/bounds.py
pynever/strategies/abstraction/bounds_propagation/manager.py
pynever/strategies/abstraction/bounds_propagation/util.py
pynever/strategies/abstraction/bounds_propagation/layers/__init__.py
pynever/strategies/abstraction/bounds_propagation/layers/affine.py
pynever/strategies/abstraction/bounds_propagation/layers/convolution.py
pynever/strategies/abstraction/bounds_propagation/layers/maxpool.py
pynever/strategies/abstraction/bounds_propagation/layers/relu.py
pynever/strategies/abstraction/bounds_propagation/test/__init__.py
pynever/strategies/abstraction/bounds_propagation/test/debugging_launcher.py
pynever/strategies/abstraction/bounds_propagation/test/generate test.ipynb
pynever/strategies/abstraction/bounds_propagation/test/generate_property.ipynb
pynever/strategies/abstraction/bounds_propagation/test/test/intermediate.vnnlib
pynever/strategies/conversion/__init__.py
pynever/strategies/conversion/representation.py
pynever-1.3.2.dist-info/licenses/LICENSE.txt
pynever-1.3.2.dist-info/METADATA
pynever-1.3.2.dist-info/WHEEL
pynever-1.3.2.dist-info/top_level.txt
pynever-1.3.2.dist-info/RECORD
