Metadata-Version: 2.4
Name: pyNeVer
Version: 1.3.2
Summary: API for the design, training and verification of neural networks.
Author-email: Dario Guidotti <dguidotti@uniss.it>, Stefano Demarchi <stefano.demarchi@edu.unige.it>
Maintainer-email: Stefano Demarchi <stefano.demarchi@edu.unige.it>, Andrea Gimelli <andrea.gimelli@edu.unige.it>
License-Expression: GPL-3.0-or-later
Project-URL: Homepage, https://neuralverification.org
Project-URL: Documentation, https://neuralverification.org/pynever
Project-URL: Repository, https://github.com/nevertools/pynever.git
Project-URL: Issues, https://github.com/nevertools/pynever/issues
Keywords: artificial intelligence,formal verification,neural networks
Classifier: Development Status :: 4 - Beta
Classifier: Topic :: Scientific/Engineering :: Artificial Intelligence
Classifier: Programming Language :: Python :: 3.11
Classifier: Operating System :: OS Independent
Requires-Python: >=3.11
License-File: LICENSE.txt
Requires-Dist: numpy
Requires-Dist: onnx
Requires-Dist: torch
Requires-Dist: torchvision
Requires-Dist: ortools
Requires-Dist: multipledispatch
Provides-Extra: docs
Requires-Dist: sphinx; extra == "docs"
Requires-Dist: sphinx-autodoc-typehints; extra == "docs"
Requires-Dist: sphinx-rtd-theme; extra == "docs"
Dynamic: license-file
